wavesongs/__init__.py
wavesongs/data/__init__.py
wavesongs/data/download.py
wavesongs/model/__init__.py
wavesongs/model/bird.py
wavesongs/model/optimizer.py
wavesongs/objects/__init__.py
wavesongs/objects/chunk.py
wavesongs/objects/song.py
wavesongs/objects/syllable.py
wavesongs/test copy.ipynb
wavesongs/utils/__init__.py
wavesongs/utils/paths.py
wavesongs/utils/plots.py
wavesongs/utils/tools.py
wavesongs-1.0.0.dist-info/LICENSE
wavesongs-1.0.0.dist-info/METADATA
wavesongs-1.0.0.dist-info/WHEEL
wavesongs-1.0.0.dist-info/RECORD
