Metadata-Version: 2.3
Name: wavesongs
Version: 1.0.0
Summary: 
License: GPL-3.0
Keywords: numerical methods,motor gestures,birdsongs
Author: saguileran@unal.edu.co
Author-email: saguileran@unal.edu.co
Maintainer: saguileran@unal.edu.co
Maintainer-email: saguileran@unal.edu.co
Requires-Python: >=3.10
Classifier: License :: OSI Approved :: GNU General Public License v3 (GPLv3)
Classifier: Programming Language :: Python :: 3
Classifier: Programming Language :: Python :: 3.10
Classifier: Programming Language :: Python :: 3.11
Classifier: Programming Language :: Python :: 3.12
Classifier: Programming Language :: Python :: 3.13
Classifier: Topic :: Software Development :: Libraries :: Python Modules
Classifier: Topic :: Software Development :: Sound Generation
Provides-Extra: dev
Provides-Extra: test
Requires-Dist: black ; extra == "dev"
Requires-Dist: ffmpeg (>=1.4,<2.0)
Requires-Dist: ipykernel (>=6.29.5,<7.0.0)
Requires-Dist: ipykernel ; extra == "dev"
Requires-Dist: ipympl (>=0.9.6,<0.10.0)
Requires-Dist: ipywidgets (<=8.0.3) ; extra == "dev"
Requires-Dist: librosa (>=0.10.2.post1,<0.11.0)
Requires-Dist: llvmlite (>=0.44.0,<0.45.0)
Requires-Dist: matplotlib (>=3.10.0,<4.0.0)
Requires-Dist: mpl-pan-zoom (>=1.0.0,<2.0.0)
Requires-Dist: mpl-point-clicker (>=0.4.1,<0.5.0)
Requires-Dist: nox ; extra == "dev"
Requires-Dist: numpy (==2.1.3)
Requires-Dist: pandas (>=2.2.3,<3.0.0)
Requires-Dist: peakutils (>=1.3.5,<2.0.0)
Requires-Dist: plotly (>=6.0.0,<7.0.0)
Requires-Dist: pytest (>=7) ; extra == "dev"
Requires-Dist: pytest (>=7) ; extra == "test"
Requires-Dist: scikit-learn (>=1.6.1,<2.0.0)
Requires-Dist: scikit-maad (>=1.4.3,<2.0.0)
Requires-Dist: sympy (>=1.13.3,<2.0.0)
Project-URL: Documentation, https://wavesongs.github.io/
Project-URL: Homepage, https://wavesongs.github.io/
Project-URL: Repository, https://github.com/wavesongs/wavesongs/
